LICENSE
ctrader_fix/__init__.py
ctrader_fix/client.py
ctrader_fix/factory.py
ctrader_fix/fixProtocol.py
ctrader_fix/messages.py
ctrader_fix-0.1.0.dist-info/LICENSE
ctrader_fix-0.1.0.dist-info/WHEEL
ctrader_fix-0.1.0.dist-info/METADATA
ctrader_fix-0.1.0.dist-info/RECORD
