Metadata-Version: 2.1
Name: ctrader-fix
Version: 0.1.0
Summary: A Python package for interacting with cTrader FIX API
Home-page: https://github.com/spotware/cTraderFixPy
License: MIT
Author: Spotware
Author-email: connect@spotware.com
Requires-Python: >=3.8,<4.0
Classifier: License :: OSI Approved :: MIT License
Classifier: Natural Language :: English
Classifier: Programming Language :: Python :: 3
Classifier: Programming Language :: Python :: 3.10
Classifier: Programming Language :: Python :: 3.8
Classifier: Programming Language :: Python :: 3.9
Requires-Dist: Twisted (==21.7.0)
Project-URL: Documentation, https://spotware.github.io/cTraderFixPy
